mail_to_sms/__init__.py
mail_to_sms/gateways.json
mail_to_sms/mail_to_sms.py
mail_to_sms/mail_to_sms_cli.py
mail_to_sms-0.3.1.dist-info/DESCRIPTION.rst
mail_to_sms-0.3.1.dist-info/METADATA
mail_to_sms-0.3.1.dist-info/RECORD
mail_to_sms-0.3.1.dist-info/WHEEL
mail_to_sms-0.3.1.dist-info/entry_points.txt
mail_to_sms-0.3.1.dist-info/metadata.json
mail_to_sms-0.3.1.dist-info/top_level.txt
