Metadata-Version: 2.0
Name: mail-to-sms
Version: 0.3.1
Summary: Programmatically send out text messages via email.
Home-page: https://github.com/naschorr/mail-to-sms
Author: Nick Schorr
Author-email: naschorr@gmail.com
License: MIT License
Keywords: sms,mms,messaging,mail,api
Platform: UNKNOWN
Classifier: Development Status :: 3 - Alpha
Classifier: Intended Audience :: Developers
Classifier: Environment :: Console
Classifier: Topic :: Utilities
Classifier: Operating System :: OS Independent
Classifier: License :: OSI Approved :: MIT License
Classifier: Natural Language :: English
Classifier: Programming Language :: Python
Classifier: Programming Language :: Python :: 2.7
Classifier: Programming Language :: Python :: 3
Classifier: Programming Language :: Python :: 3.5
Requires-Dist: click (>=6.7)
Requires-Dist: keyring (>=10.4)
Requires-Dist: phonenumbers (>=8.4)
Requires-Dist: yagmail (>=0.6)
